public_data_extractor_for_meetup_com-0.1.0.dist-info/licenses/LICENSE.txt
publicdataextractorformeetupcom/__init__.py
publicdataextractorformeetupcom/__main__.py
publicdataextractorformeetupcom/worker.py
public_data_extractor_for_meetup_com-0.1.0.dist-info/METADATA
public_data_extractor_for_meetup_com-0.1.0.dist-info/WHEEL
public_data_extractor_for_meetup_com-0.1.0.dist-info/top_level.txt
public_data_extractor_for_meetup_com-0.1.0.dist-info/RECORD
