Metadata-Version: 2.4
Name: public-data-extractor-for-meetup-com
Version: 0.1.0
Summary: Public Data Extractor for meetup.com
Requires-Python: >=3.10
License-File: LICENSE.txt
Requires-Dist: requests
Requires-Dist: PyJWT
Requires-Dist: cryptography
Provides-Extra: dev
Requires-Dist: pytest; extra == "dev"
Requires-Dist: black; extra == "dev"
Requires-Dist: isort; extra == "dev"
Requires-Dist: flake8; extra == "dev"
Dynamic: license-file
